README.md
setup.cfg
setup.py
distributions/Binomialdistribution.py
distributions/Gaussiandistribution.py
distributions/Generaldistribution.py
distributions/__init__.py
jay_distributions.egg-info/PKG-INFO
jay_distributions.egg-info/SOURCES.txt
jay_distributions.egg-info/dependency_links.txt
jay_distributions.egg-info/not-zip-safe
jay_distributions.egg-info/top_level.txt