Metadata-Version: 1.0
Name: jay-distributions
Version: 0.1
Summary: Gaussian and Binomial distributions
Home-page: UNKNOWN
Author: Jay Xu
Author-email: UNKNOWN
License: UNKNOWN
Platform: UNKNOWN
